{"map":[[{"tileType":"sea","cutLocationX":12,"cutLocationY":1,"size":16,"tileValue":0},{"tileType":"sea","cutLocationX":12,"cutLocationY":1,"size":16,"tileValue":0},{"tileType":"sea","cutLocationX":12,"cutLocationY":1,"size":16,"tileValue":0},{"tileType":"sea","cutLocationX":12,"cutLocationY":1,"size":16,"tileValue":0},{"tileType":"sea","cutLocationX":12,"cutLocationY":1,"size":16,"tileValue":0},{"tileType":"sea","cutLocationX":12,"cutLocationY":1,"size":16,"tileValue":0},{"tileType":"sea","cutLocationX":12,"cutLocationY":1,"size":16,"tileValue":0},{"tileType":"sea","cutLocationX":12,"cutLocationY":1,"size":16,"tileValue":0},{"tileType":"sea","cutLocationX":12,"cutLocationY":1,"size":16,"tileValue":0},{"tileType":"sea","cutLocationX":12,"cutLocationY":1,"size":16,"tileValue":0}],[{"tileType":"sea","cutLocationX":12,"cutLocationY":1,"size":16,"tileValue":0},{"tileType":"sea","cutLocationX":12,"cutLocationY":1,"size":16,"tileValue":0},{"tileType":"sea","cutLocationX":12,"cutLocationY":1,"size":16,"tileValue":0},{"tileType":"sea","cutLocationX":12,"cutLocationY":1,"size":16,"tileValue":0},{"tileType":"sea","cutLocationX":12,"cutLocationY":1,"size":16,"tileValue":0},{"tileType":"sea","cutLocationX":12,"cutLocationY":1,"size":16,"tileValue":0},{"tileType":"sea","cutLocationX":12,"cutLocationY":1,"size":16,"tileValue":0},{"tileType":"sea","cutLocationX":12,"cutLocationY":1,"size":16,"tileValue":0},{"tileType":"sea","cutLocationX":12,"cutLocationY":1,"size":16,"tileValue":0},{"tileType":"sea","cutLocationX":12,"cutLocationY":1,"size":16,"tileValue":0}],[{"tileType":"sea","cutLocationX":12,"cutLocationY":1,"size":16,"tileValue":0},{"tileType":"sea","cutLocationX":12,"cutLocationY":1,"size":16,"tileValue":0},{"tileType":"sea","cutLocationX":12,"cutLocationY":1,"size":16,"tileValue":0},{"tileType":"sea","cutLocationX":12,"cutLocationY":1,"size":16,"tileValue":0},{"tileType":"sea","cutLocationX":12,"cutLocationY":1,"size":16,"tileValue":0},{"tileType":"sea","cutLocationX":12,"cutLocationY":1,"size":16,"tileValue":0},{"tileType":"sea","cutLocationX":12,"cutLocationY":1,"size":16,"tileValue":0},{"tileType":"sea","cutLocationX":12,"cutLocationY":1,"size":16,"tileValue":0},{"tileType":"sea","cutLocationX":12,"cutLocationY":1,"size":16,"tileValue":0},{"tileType":"sea","cutLocationX":12,"cutLocationY":1,"size":16,"tileValue":0}],[{"tileType":"sea","cutLocationX":12,"cutLocationY":1,"size":16,"tileValue":0},{"tileType":"sea","cutLocationX":12,"cutLocationY":1,"size":16,"tileValue":0},{"tileType":"sea","cutLocationX":12,"cutLocationY":1,"size":16,"tileValue":0},{"tileType":"sea","cutLocationX":12,"cutLocationY":1,"size":16,"tileValue":0},{"tileType":"sea","cutLocationX":12,"cutLocationY":1,"size":16,"tileValue":0},{"tileType":"sea","cutLocationX":12,"cutLocationY":1,"size":16,"tileValue":0},{"tileType":"sea","cutLocationX":12,"cutLocationY":1,"size":16,"tileValue":0},{"tileType":"sea","cutLocationX":12,"cutLocationY":1,"size":16,"tileValue":0},{"tileType":"sea","cutLocationX":12,"cutLocationY":1,"size":16,"tileValue":0},{"tileType":"sea","cutLocationX":12,"cutLocationY":1,"size":16,"tileValue":0}],[{"tileType":"sea","cutLocationX":12,"cutLocationY":1,"size":16,"tileValue":0},{"tileType":"sea","cutLocationX":12,"cutLocationY":1,"size":16,"tileValue":0},{"tileType":"sea","cutLocationX":12,"cutLocationY":1,"size":16,"tileValue":0},{"tileType":"sea","cutLocationX":12,"cutLocationY":1,"size":16,"tileValue":0},{"tileType":"sea","cutLocationX":12,"cutLocationY":1,"size":16,"tileValue":0},{"tileType":"sea","cutLocationX":12,"cutLocationY":1,"size":16,"tileValue":0},{"tileType":"sea","cutLocationX":12,"cutLocationY":1,"size":16,"tileValue":0},{"tileType":"sea","cutLocationX":12,"cutLocationY":1,"size":16,"tileValue":0},{"tileType":"sea","cutLocationX":12,"cutLocationY":1,"size":16,"tileValue":0},{"tileType":"sea","cutLocationX":12,"cutLocationY":1,"size":16,"tileValue":0}],[{"tileType":"sea","cutLocationX":12,"cutLocationY":1,"size":16,"tileValue":0},{"tileType":"sea","cutLocationX":12,"cutLocationY":1,"size":16,"tileValue":0},{"tileType":"sea","cutLocationX":12,"cutLocationY":1,"size":16,"tileValue":0},{"tileType":"sea","cutLocationX":12,"cutLocationY":1,"size":16,"tileValue":0},{"tileType":"sea","cutLocationX":12,"cutLocationY":1,"size":16,"tileValue":0},{"tileType":"sea","cutLocationX":12,"cutLocationY":1,"size":16,"tileValue":0},{"tileType":"sea","cutLocationX":12,"cutLocationY":1,"size":16,"tileValue":0},{"tileType":"sea","cutLocationX":12,"cutLocationY":1,"size":16,"tileValue":0},{"tileType":"sea","cutLocationX":12,"cutLocationY":1,"size":16,"tileValue":0},{"tileType":"sea","cutLocationX":12,"cutLocationY":1,"size":16,"tileValue":0}],[{"tileType":"sea","cutLocationX":12,"cutLocationY":1,"size":16,"tileValue":0},{"tileType":"sea","cutLocationX":12,"cutLocationY":1,"size":16,"tileValue":0},{"tileType":"sea","cutLocationX":12,"cutLocationY":1,"size":16,"tileValue":0},{"tileType":"sea","cutLocationX":12,"cutLocationY":1,"size":16,"tileValue":0},{"tileType":"sea","cutLocationX":12,"cutLocationY":1,"size":16,"tileValue":0},{"tileType":"sea","cutLocationX":12,"cutLocationY":1,"size":16,"tileValue":0},{"tileType":"sea","cutLocationX":12,"cutLocationY":1,"size":16,"tileValue":0},{"tileType":"sea","cutLocationX":12,"cutLocationY":1,"size":16,"tileValue":0},{"tileType":"sea","cutLocationX":12,"cutLocationY":1,"size":16,"tileValue":0},{"tileType":"sea","cutLocationX":12,"cutLocationY":1,"size":16,"tileValue":0}],[{"tileType":"sea","cutLocationX":12,"cutLocationY":1,"size":16,"tileValue":0},{"tileType":"sea","cutLocationX":12,"cutLocationY":1,"size":16,"tileValue":0},{"tileType":"sea","cutLocationX":12,"cutLocationY":1,"size":16,"tileValue":0},{"tileType":"sea","cutLocationX":12,"cutLocationY":1,"size":16,"tileValue":0},{"tileType":"sea","cutLocationX":12,"cutLocationY":1,"size":16,"tileValue":0},{"tileType":"sea","cutLocationX":12,"cutLocationY":1,"size":16,"tileValue":0},{"tileType":"sea","cutLocationX":12,"cutLocationY":1,"size":16,"tileValue":0},{"tileType":"sea","cutLocationX":12,"cutLocationY":1,"size":16,"tileValue":0},{"tileType":"sea","cutLocationX":12,"cutLocationY":1,"size":16,"tileValue":0},{"tileType":"sea","cutLocationX":12,"cutLocationY":1,"size":16,"tileValue":0}],[{"tileType":"sea","cutLocationX":12,"cutLocationY":1,"size":16,"tileValue":0},{"tileType":"sea","cutLocationX":12,"cutLocationY":1,"size":16,"tileValue":0},{"tileType":"sea","cutLocationX":12,"cutLocationY":1,"size":16,"tileValue":0},{"tileType":"sea","cutLocationX":12,"cutLocationY":1,"size":16,"tileValue":0},{"tileType":"sea","cutLocationX":12,"cutLocationY":1,"size":16,"tileValue":0},{"tileType":"ground","cutLocationX":4.5,"cutLocationY":0,"size":32,"tileValue":10},{"tileType":"ground","cutLocationX":4.5,"cutLocationY":0,"size":32,"tileValue":10},{"tileType":"ground","cutLocationX":4.5,"cutLocationY":0,"size":32,"tileValue":10},{"tileType":"sea","cutLocationX":12,"cutLocationY":1,"size":16,"tileValue":0},{"tileType":"sea","cutLocationX":12,"cutLocationY":1,"size":16,"tileValue":0}],[{"tileType":"sea","cutLocationX":12,"cutLocationY":1,"size":16,"tileValue":0},{"tileType":"sea","cutLocationX":12,"cutLocationY":1,"size":16,"tileValue":0},{"tileType":"sea","cutLocationX":12,"cutLocationY":1,"size":16,"tileValue":0},{"tileType":"sea","cutLocationX":12,"cutLocationY":1,"size":16,"tileValue":0},{"tileType":"ground","cutLocationX":4.5,"cutLocationY":0,"size":32,"tileValue":10},{"tileType":"ground","cutLocationX":4.5,"cutLocationY":0,"size":32,"tileValue":10},{"tileType":"ground","cutLocationX":4.5,"cutLocationY":0,"size":32,"tileValue":10},{"tileType":"ground","cutLocationX":4.5,"cutLocationY":0,"size":32,"tileValue":10},{"tileType":"ground","cutLocationX":4.5,"cutLocationY":0,"size":32,"tileValue":10},{"tileType":"sea","cutLocationX":12,"cutLocationY":1,"size":16,"tileValue":0}],[{"tileType":"sea","cutLocationX":12,"cutLocationY":1,"size":16,"tileValue":0},{"tileType":"sea","cutLocationX":12,"cutLocationY":1,"size":16,"tileValue":0},{"tileType":"sea","cutLocationX":12,"cutLocationY":1,"size":16,"tileValue":0},{"tileType":"sea","cutLocationX":12,"cutLocationY":1,"size":16,"tileValue":0},{"tileType":"ground","cutLocationX":4.5,"cutLocationY":0,"size":32,"tileValue":10},{"tileType":"ground","cutLocationX":4.5,"cutLocationY":0,"size":32,"tileValue":10},{"tileType":"ground","cutLocationX":4.5,"cutLocationY":0,"size":32,"tileValue":10},{"tileType":"ground","cutLocationX":4.5,"cutLocationY":0,"size":32,"tileValue":10},{"tileType":"ground","cutLocationX":4.5,"cutLocationY":0,"size":32,"tileValue":10},{"tileType":"sea","cutLocationX":12,"cutLocationY":1,"size":16,"tileValue":0}],[{"tileType":"sea","cutLocationX":12,"cutLocationY":1,"size":16,"tileValue":0},{"tileType":"sea","cutLocationX":12,"cutLocationY":1,"size":16,"tileValue":0},{"tileType":"sea","cutLocationX":12,"cutLocationY":1,"size":16,"tileValue":0},{"tileType":"sea","cutLocationX":12,"cutLocationY":1,"size":16,"tileValue":0},{"tileType":"ground","cutLocationX":4.5,"cutLocationY":0,"size":32,"tileValue":10},{"tileType":"ground","cutLocationX":4.5,"cutLocationY":0,"size":32,"tileValue":10},{"tileType":"ground","cutLocationX":4.5,"cutLocationY":0,"size":32,"tileValue":10},{"tileType":"ground","cutLocationX":4.5,"cutLocationY":0,"size":32,"tileValue":10},{"tileType":"ground","cutLocationX":4.5,"cutLocationY":0,"size":32,"tileValue":10},{"tileType":"sea","cutLocationX":12,"cutLocationY":1,"size":16,"tileValue":0}],[{"tileType":"sea","cutLocationX":12,"cutLocationY":1,"size":16,"tileValue":0},{"tileType":"sea","cutLocationX":12,"cutLocationY":1,"size":16,"tileValue":0},{"tileType":"sea","cutLocationX":12,"cutLocationY":1,"size":16,"tileValue":0},{"tileType":"sea","cutLocationX":12,"cutLocationY":1,"size":16,"tileValue":0},{"tileType":"sea","cutLocationX":12,"cutLocationY":1,"size":16,"tileValue":0},{"tileType":"ground","cutLocationX":4.5,"cutLocationY":0,"size":32,"tileValue":10},{"tileType":"ground","cutLocationX":4.5,"cutLocationY":0,"size":32,"tileValue":10},{"tileType":"ground","cutLocationX":4.5,"cutLocationY":0,"size":32,"tileValue":10},{"tileType":"sea","cutLocationX":12,"cutLocationY":1,"size":16,"tileValue":0},{"tileType":"sea","cutLocationX":12,"cutLocationY":1,"size":16,"tileValue":0}],[{"tileType":"sea","cutLocationX":12,"cutLocationY":1,"size":16,"tileValue":0},{"tileType":"sea","cutLocationX":12,"cutLocationY":1,"size":16,"tileValue":0},{"tileType":"sea","cutLocationX":12,"cutLocationY":1,"size":16,"tileValue":0},{"tileType":"sea","cutLocationX":12,"cutLocationY":1,"size":16,"tileValue":0},{"tileType":"sea","cutLocationX":12,"cutLocationY":1,"size":16,"tileValue":0},{"tileType":"sea","cutLocationX":12,"cutLocationY":1,"size":16,"tileValue":0},{"tileType":"sea","cutLocationX":12,"cutLocationY":1,"size":16,"tileValue":0},{"tileType":"sea","cutLocationX":12,"cutLocationY":1,"size":16,"tileValue":0},{"tileType":"sea","cutLocationX":12,"cutLocationY":1,"size":16,"tileValue":0},{"tileType":"sea","cutLocationX":12,"cutLocationY":1,"size":16,"tileValue":0}],[{"tileType":"sea","cutLocationX":12,"cutLocationY":1,"size":16,"tileValue":0},{"tileType":"sea","cutLocationX":12,"cutLocationY":1,"size":16,"tileValue":0},{"tileType":"sea","cutLocationX":12,"cutLocationY":1,"size":16,"tileValue":0},{"tileType":"sea","cutLocationX":12,"cutLocationY":1,"size":16,"tileValue":0},{"tileType":"sea","cutLocationX":12,"cutLocationY":1,"size":16,"tileValue":0},{"tileType":"sea","cutLocationX":12,"cutLocationY":1,"size":16,"tileValue":0},{"tileType":"sea","cutLocationX":12,"cutLocationY":1,"size":16,"tileValue":0},{"tileType":"sea","cutLocationX":12,"cutLocationY":1,"size":16,"tileValue":0},{"tileType":"sea","cutLocationX":12,"cutLocationY":1,"size":16,"tileValue":0},{"tileType":"sea","cutLocationX":12,"cutLocationY":1,"size":16,"tileValue":0}],[{"tileType":"sea","cutLocationX":12,"cutLocationY":1,"size":16,"tileValue":0},{"tileType":"sea","cutLocationX":12,"cutLocationY":1,"size":16,"tileValue":0},{"tileType":"sea","cutLocationX":12,"cutLocationY":1,"size":16,"tileValue":0},{"tileType":"sea","cutLocationX":12,"cutLocationY":1,"size":16,"tileValue":0},{"tileType":"sea","cutLocationX":12,"cutLocationY":1,"size":16,"tileValue":0},{"tileType":"sea","cutLocationX":12,"cutLocationY":1,"size":16,"tileValue":0},{"tileType":"sea","cutLocationX":12,"cutLocationY":1,"size":16,"tileValue":0},{"tileType":"sea","cutLocationX":12,"cutLocationY":1,"size":16,"tileValue":0},{"tileType":"sea","cutLocationX":12,"cutLocationY":1,"size":16,"tileValue":0},{"tileType":"sea","cutLocationX":12,"cutLocationY":1,"size":16,"tileValue":0}],[{"tileType":"sea","cutLocationX":12,"cutLocationY":1,"size":16,"tileValue":0},{"tileType":"sea","cutLocationX":12,"cutLocationY":1,"size":16,"tileValue":0},{"tileType":"sea","cutLocationX":12,"cutLocationY":1,"size":16,"tileValue":0},{"tileType":"sea","cutLocationX":12,"cutLocationY":1,"size":16,"tileValue":0},{"tileType":"sea","cutLocationX":12,"cutLocationY":1,"size":16,"tileValue":0},{"tileType":"sea","cutLocationX":12,"cutLocationY":1,"size":16,"tileValue":0},{"tileType":"sea","cutLocationX":12,"cutLocationY":1,"size":16,"tileValue":0},{"tileType":"sea","cutLocationX":12,"cutLocationY":1,"size":16,"tileValue":0},{"tileType":"sea","cutLocationX":12,"cutLocationY":1,"size":16,"tileValue":0},{"tileType":"sea","cutLocationX":12,"cutLocationY":1,"size":16,"tileValue":0}],[{"tileType":"sea","cutLocationX":12,"cutLocationY":1,"size":16,"tileValue":0},{"tileType":"sea","cutLocationX":12,"cutLocationY":1,"size":16,"tileValue":0},{"tileType":"sea","cutLocationX":12,"cutLocationY":1,"size":16,"tileValue":0},{"tileType":"sea","cutLocationX":12,"cutLocationY":1,"size":16,"tileValue":0},{"tileType":"sea","cutLocationX":12,"cutLocationY":1,"size":16,"tileValue":0},{"tileType":"sea","cutLocationX":12,"cutLocationY":1,"size":16,"tileValue":0},{"tileType":"sea","cutLocationX":12,"cutLocationY":1,"size":16,"tileValue":0},{"tileType":"sea","cutLocationX":12,"cutLocationY":1,"size":16,"tileValue":0},{"tileType":"sea","cutLocationX":12,"cutLocationY":1,"size":16,"tileValue":0},{"tileType":"sea","cutLocationX":12,"cutLocationY":1,"size":16,"tileValue":0}],[{"tileType":"sea","cutLocationX":12,"cutLocationY":1,"size":16,"tileValue":0},{"tileType":"sea","cutLocationX":12,"cutLocationY":1,"size":16,"tileValue":0},{"tileType":"sea","cutLocationX":12,"cutLocationY":1,"size":16,"tileValue":0},{"tileType":"sea","cutLocationX":12,"cutLocationY":1,"size":16,"tileValue":0},{"tileType":"sea","cutLocationX":12,"cutLocationY":1,"size":16,"tileValue":0},{"tileType":"sea","cutLocationX":12,"cutLocationY":1,"size":16,"tileValue":0},{"tileType":"sea","cutLocationX":12,"cutLocationY":1,"size":16,"tileValue":0},{"tileType":"sea","cutLocationX":12,"cutLocationY":1,"size":16,"tileValue":0},{"tileType":"sea","cutLocationX":12,"cutLocationY":1,"size":16,"tileValue":0},{"tileType":"sea","cutLocationX":12,"cutLocationY":1,"size":16,"tileValue":0}],[{"tileType":"sea","cutLocationX":12,"cutLocationY":1,"size":16,"tileValue":0},{"tileType":"sea","cutLocationX":12,"cutLocationY":1,"size":16,"tileValue":0},{"tileType":"sea","cutLocationX":12,"cutLocationY":1,"size":16,"tileValue":0},{"tileType":"sea","cutLocationX":12,"cutLocationY":1,"size":16,"tileValue":0},{"tileType":"sea","cutLocationX":12,"cutLocationY":1,"size":16,"tileValue":0},{"tileType":"sea","cutLocationX":12,"cutLocationY":1,"size":16,"tileValue":0},{"tileType":"sea","cutLocationX":12,"cutLocationY":1,"size":16,"tileValue":0},{"tileType":"sea","cutLocationX":12,"cutLocationY":1,"size":16,"tileValue":0},{"tileType":"sea","cutLocationX":12,"cutLocationY":1,"size":16,"tileValue":0},{"tileType":"sea","cutLocationX":12,"cutLocationY":1,"size":16,"tileValue":0}],[{"tileType":"sea","cutLocationX":12,"cutLocationY":1,"size":16,"tileValue":0},{"tileType":"sea","cutLocationX":12,"cutLocationY":1,"size":16,"tileValue":0},{"tileType":"sea","cutLocationX":12,"cutLocationY":1,"size":16,"tileValue":0},{"tileType":"sea","cutLocationX":12,"cutLocationY":1,"size":16,"tileValue":0},{"tileType":"sea","cutLocationX":12,"cutLocationY":1,"size":16,"tileValue":0},{"tileType":"sea","cutLocationX":12,"cutLocationY":1,"size":16,"tileValue":0},{"tileType":"sea","cutLocationX":12,"cutLocationY":1,"size":16,"tileValue":0},{"tileType":"sea","cutLocationX":12,"cutLocationY":1,"size":16,"tileValue":0},{"tileType":"sea","cutLocationX":12,"cutLocationY":1,"size":16,"tileValue":0},{"tileType":"sea","cutLocationX":12,"cutLocationY":1,"size":16,"tileValue":0}]],"game_item_record":{"x19y10":{"plantType":{"name":"carrot","stage0cutX":1,"stage0cutY":0,"stage1cutX":3,"stage1cutY":0,"stage2cutX":5,"stage2cutY":0,"stage3cutX":0,"stage3cutY":33,"size":16},"stageChangeAt":1657698127298,"stage":0,"x":19,"y":10},"x19y11":{"plantType":{"name":"carrot","stage0cutX":1,"stage0cutY":0,"stage1cutX":3,"stage1cutY":0,"stage2cutX":5,"stage2cutY":0,"stage3cutX":0,"stage3cutY":33,"size":16},"stageChangeAt":1657698127427,"stage":0,"x":19,"y":11},"x20y11":{"plantType":{"name":"carrot","stage0cutX":1,"stage0cutY":0,"stage1cutX":3,"stage1cutY":0,"stage2cutX":5,"stage2cutY":0,"stage3cutX":0,"stage3cutY":33,"size":16},"stageChangeAt":1657698127443,"stage":0,"x":20,"y":11},"x20y12":{"plantType":{"name":"carrot","stage0cutX":1,"stage0cutY":0,"stage1cutX":3,"stage1cutY":0,"stage2cutX":5,"stage2cutY":0,"stage3cutX":0,"stage3cutY":33,"size":16},"stageChangeAt":1657698127493,"stage":0,"x":20,"y":12},"x20y13":{"plantType":{"name":"carrot","stage0cutX":1,"stage0cutY":0,"stage1cutX":3,"stage1cutY":0,"stage2cutX":5,"stage2cutY":0,"stage3cutX":0,"stage3cutY":33,"size":16},"stageChangeAt":1657698127526,"stage":0,"x":20,"y":13},"x20y14":{"plantType":{"name":"carrot","stage0cutX":1,"stage0cutY":0,"stage1cutX":3,"stage1cutY":0,"stage2cutX":5,"stage2cutY":0,"stage3cutX":0,"stage3cutY":33,"size":16},"stageChangeAt":1657698127560,"stage":0,"x":20,"y":14},"x19y14":{"plantType":{"name":"carrot","stage0cutX":1,"stage0cutY":0,"stage1cutX":3,"stage1cutY":0,"stage2cutX":5,"stage2cutY":0,"stage3cutX":0,"stage3cutY":33,"size":16},"stageChangeAt":1657698127577,"stage":0,"x":19,"y":14},"x19y15":{"plantType":{"name":"carrot","stage0cutX":1,"stage0cutY":0,"stage1cutX":3,"stage1cutY":0,"stage2cutX":5,"stage2cutY":0,"stage3cutX":0,"stage3cutY":33,"size":16},"stageChangeAt":1657698127609,"stage":0,"x":19,"y":15},"x20y16":{"plantType":{"name":"carrot","stage0cutX":1,"stage0cutY":0,"stage1cutX":3,"stage1cutY":0,"stage2cutX":5,"stage2cutY":0,"stage3cutX":0,"stage3cutY":33,"size":16},"stageChangeAt":1657698127760,"stage":0,"x":20,"y":16},"x20y15":{"plantType":{"name":"carrot","stage0cutX":1,"stage0cutY":0,"stage1cutX":3,"stage1cutY":0,"stage2cutX":5,"stage2cutY":0,"stage3cutX":0,"stage3cutY":33,"size":16},"stageChangeAt":1657698127943,"stage":0,"x":20,"y":15},"x18y15":{"plantType":{"name":"carrot","stage0cutX":1,"stage0cutY":0,"stage1cutX":3,"stage1cutY":0,"stage2cutX":5,"stage2cutY":0,"stage3cutX":0,"stage3cutY":33,"size":16},"stageChangeAt":1657698127977,"stage":0,"x":18,"y":15},"x17y14":{"plantType":{"name":"carrot","stage0cutX":1,"stage0cutY":0,"stage1cutX":3,"stage1cutY":0,"stage2cutX":5,"stage2cutY":0,"stage3cutX":0,"stage3cutY":33,"size":16},"stageChangeAt":1657698127994,"stage":0,"x":17,"y":14},"x17y13":{"plantType":{"name":"carrot","stage0cutX":1,"stage0cutY":0,"stage1cutX":3,"stage1cutY":0,"stage2cutX":5,"stage2cutY":0,"stage3cutX":0,"stage3cutY":33,"size":16},"stageChangeAt":1657698128060,"stage":0,"x":17,"y":13},"x18y12":{"plantType":{"name":"carrot","stage0cutX":1,"stage0cutY":0,"stage1cutX":3,"stage1cutY":0,"stage2cutX":5,"stage2cutY":0,"stage3cutX":0,"stage3cutY":33,"size":16},"stageChangeAt":1657698128093,"stage":0,"x":18,"y":12},"x19y12":{"plantType":{"name":"carrot","stage0cutX":1,"stage0cutY":0,"stage1cutX":3,"stage1cutY":0,"stage2cutX":5,"stage2cutY":0,"stage3cutX":0,"stage3cutY":33,"size":16},"stageChangeAt":1657698128143,"stage":0,"x":19,"y":12},"x19y13":{"plantType":{"name":"carrot","stage0cutX":1,"stage0cutY":0,"stage1cutX":3,"stage1cutY":0,"stage2cutX":5,"stage2cutY":0,"stage3cutX":0,"stage3cutY":33,"size":16},"stageChangeAt":1657698128327,"stage":0,"x":19,"y":13},"x18y13":{"plantType":{"name":"carrot","stage0cutX":1,"stage0cutY":0,"stage1cutX":3,"stage1cutY":0,"stage2cutX":5,"stage2cutY":0,"stage3cutX":0,"stage3cutY":33,"size":16},"stageChangeAt":1657698128544,"stage":0,"x":18,"y":13},"x17y11":{"plantType":{"name":"carrot","stage0cutX":1,"stage0cutY":0,"stage1cutX":3,"stage1cutY":0,"stage2cutX":5,"stage2cutY":0,"stage3cutX":0,"stage3cutY":33,"size":16},"stageChangeAt":1657698128976,"stage":0,"x":17,"y":11},"x17y10":{"plantType":{"name":"carrot","stage0cutX":1,"stage0cutY":0,"stage1cutX":3,"stage1cutY":0,"stage2cutX":5,"stage2cutY":0,"stage3cutX":0,"stage3cutY":33,"size":16},"stageChangeAt":1657698129010,"stage":0,"x":17,"y":10},"x17y12":{"plantType":{"name":"carrot","stage0cutX":1,"stage0cutY":0,"stage1cutX":3,"stage1cutY":0,"stage2cutX":5,"stage2cutY":0,"stage3cutX":0,"stage3cutY":33,"size":16},"stageChangeAt":1657698129227,"stage":0,"x":17,"y":12},"x17y15":{"plantType":{"name":"carrot","stage0cutX":1,"stage0cutY":0,"stage1cutX":3,"stage1cutY":0,"stage2cutX":5,"stage2cutY":0,"stage3cutX":0,"stage3cutY":33,"size":16},"stageChangeAt":1657698129377,"stage":0,"x":17,"y":15},"x16y15":{"plantType":{"name":"carrot","stage0cutX":1,"stage0cutY":0,"stage1cutX":3,"stage1cutY":0,"stage2cutX":5,"stage2cutY":0,"stage3cutX":0,"stage3cutY":33,"size":16},"stageChangeAt":1657698129393,"stage":0,"x":16,"y":15},"x18y16":{"plantType":{"name":"carrot","stage0cutX":1,"stage0cutY":0,"stage1cutX":3,"stage1cutY":0,"stage2cutX":5,"stage2cutY":0,"stage3cutX":0,"stage3cutY":33,"size":16},"stageChangeAt":1657698129660,"stage":0,"x":18,"y":16},"x18y17":{"plantType":{"name":"carrot","stage0cutX":1,"stage0cutY":0,"stage1cutX":3,"stage1cutY":0,"stage2cutX":5,"stage2cutY":0,"stage3cutX":0,"stage3cutY":33,"size":16},"stageChangeAt":1657698129676,"stage":0,"x":18,"y":17},"x19y17":{"plantType":{"name":"carrot","stage0cutX":1,"stage0cutY":0,"stage1cutX":3,"stage1cutY":0,"stage2cutX":5,"stage2cutY":0,"stage3cutX":0,"stage3cutY":33,"size":16},"stageChangeAt":1657698129694,"stage":0,"x":19,"y":17},"x19y16":{"plantType":{"name":"carrot","stage0cutX":1,"stage0cutY":0,"stage1cutX":3,"stage1cutY":0,"stage2cutX":5,"stage2cutY":0,"stage3cutX":0,"stage3cutY":33,"size":16},"stageChangeAt":1657698129793,"stage":0,"x":19,"y":16},"x18y14":{"plantType":{"name":"carrot","stage0cutX":1,"stage0cutY":0,"stage1cutX":3,"stage1cutY":0,"stage2cutX":5,"stage2cutY":0,"stage3cutX":0,"stage3cutY":33,"size":16},"stageChangeAt":1657698129960,"stage":0,"x":18,"y":14},"x16y14":{"plantType":{"name":"carrot","stage0cutX":1,"stage0cutY":0,"stage1cutX":3,"stage1cutY":0,"stage2cutX":5,"stage2cutY":0,"stage3cutX":0,"stage3cutY":33,"size":16},"stageChangeAt":1657698130327,"stage":0,"x":16,"y":14},"x16y13":{"plantType":{"name":"carrot","stage0cutX":1,"stage0cutY":0,"stage1cutX":3,"stage1cutY":0,"stage2cutX":5,"stage2cutY":0,"stage3cutX":0,"stage3cutY":33,"size":16},"stageChangeAt":1657698130376,"stage":0,"x":16,"y":13},"x16y12":{"plantType":{"name":"carrot","stage0cutX":1,"stage0cutY":0,"stage1cutX":3,"stage1cutY":0,"stage2cutX":5,"stage2cutY":0,"stage3cutX":0,"stage3cutY":33,"size":16},"stageChangeAt":1657698130443,"stage":0,"x":16,"y":12},"x18y8":{"plantType":{"name":"carrot","stage0cutX":1,"stage0cutY":0,"stage1cutX":3,"stage1cutY":0,"stage2cutX":5,"stage2cutY":0,"stage3cutX":0,"stage3cutY":33,"size":16},"stageChangeAt":1657698130743,"stage":0,"x":18,"y":8},"x19y9":{"plantType":{"name":"carrot","stage0cutX":1,"stage0cutY":0,"stage1cutX":3,"stage1cutY":0,"stage2cutX":5,"stage2cutY":0,"stage3cutX":0,"stage3cutY":33,"size":16},"stageChangeAt":1657698130776,"stage":0,"x":19,"y":9},"x20y9":{"plantType":{"name":"carrot","stage0cutX":1,"stage0cutY":0,"stage1cutX":3,"stage1cutY":0,"stage2cutX":5,"stage2cutY":0,"stage3cutX":0,"stage3cutY":33,"size":16},"stageChangeAt":1657698130826,"stage":0,"x":20,"y":9},"x20y10":{"plantType":{"name":"carrot","stage0cutX":1,"stage0cutY":0,"stage1cutX":3,"stage1cutY":0,"stage2cutX":5,"stage2cutY":0,"stage3cutX":0,"stage3cutY":33,"size":16},"stageChangeAt":1657698130843,"stage":0,"x":20,"y":10},"x18y11":{"plantType":{"name":"carrot","stage0cutX":1,"stage0cutY":0,"stage1cutX":3,"stage1cutY":0,"stage2cutX":5,"stage2cutY":0,"stage3cutX":0,"stage3cutY":33,"size":16},"stageChangeAt":1657698131077,"stage":0,"x":18,"y":11},"x18y10":{"plantType":{"name":"carrot","stage0cutX":1,"stage0cutY":0,"stage1cutX":3,"stage1cutY":0,"stage2cutX":5,"stage2cutY":0,"stage3cutX":0,"stage3cutY":33,"size":16},"stageChangeAt":1657698131110,"stage":0,"x":18,"y":10}},"lastCheckingTime":1657685390966,"lastScoreRecord":{"score":0},"scoreFactorList":{"carrot":{"items_id":1,"items_name":"carrot","stage_0_score":null,"stage_1_score":null,"stage_2_score":null,"stage_3_score":null},"corn":{"items_id":2,"items_name":"corn","stage_0_score":null,"stage_1_score":null,"stage_2_score":null,"stage_3_score":null},"yellow_flower":{"items_id":3,"items_name":"yellow_flower","stage_0_score":null,"stage_1_score":null,"stage_2_score":null,"stage_3_score":null},"red_flower":{"items_id":4,"items_name":"red_flower","stage_0_score":null,"stage_1_score":null,"stage_2_score":null,"stage_3_score":null},"blue_flower":{"items_id":5,"items_name":"blue_flower","stage_0_score":null,"stage_1_score":null,"stage_2_score":null,"stage_3_score":null},"pumpkin":{"items_id":6,"items_name":"pumpkin","stage_0_score":null,"stage_1_score":null,"stage_2_score":null,"stage_3_score":null},"lettuce":{"items_id":7,"items_name":"lettuce","stage_0_score":null,"stage_1_score":null,"stage_2_score":null,"stage_3_score":null},"green_trees":{"items_id":8,"items_name":"green_trees","stage_0_score":null,"stage_1_score":null,"stage_2_score":null,"stage_3_score":null},"brown_trees":{"items_id":9,"items_name":"brown_trees","stage_0_score":null,"stage_1_score":null,"stage_2_score":null,"stage_3_score":null},"small_house":{"items_id":10,"items_name":"small_house","stage_0_score":null,"stage_1_score":null,"stage_2_score":null,"stage_3_score":null},"big_house":{"items_id":11,"items_name":"big_house","stage_0_score":null,"stage_1_score":null,"stage_2_score":null,"stage_3_score":null}}}